takauma/__init__.py
takauma/hakemisto.py
takauma/jakelu.py
takauma/luokka.py
takauma/moduuli.py
python_takauma-0.6.3.dist-info/METADATA
python_takauma-0.6.3.dist-info/WHEEL
python_takauma-0.6.3.dist-info/historia.json
python_takauma-0.6.3.dist-info/top_level.txt
python_takauma-0.6.3.dist-info/RECORD
