Metadata-Version: 2.4
Name: python-takauma
Version: 0.6.3
Summary: Python-moduulien tiedostoversiointi
Author-email: Antti Hautaniemi <antti.hautaniemi@me.com>
Project-URL: Repository, https://github.com/an7oine/python-takauma.git
Requires-Python: >=3.8
Requires-Dist: python-mmaare
Provides-Extra: kehitys
Requires-Dist: git-versiointi>=1.4.4; extra == "kehitys"
